{
  "main": {
    "id": "1b945fe229b91a05",
    "type": "split",
    "children": [
      {
        "id": "fb9afdf7913fa0e8",
        "type": "tabs",
        "children": [
          {
            "id": "d8fd5ec142f88edc",
            "type": "leaf",
            "state": {
              "type": "markdown",
              "state": {
                "file": "Unrealistic Roadmap.md",
                "mode": "source",
                "source": false
              },
              "icon": "lucide-file",
              "title": "Unrealistic Roadmap"
            }
          },
          {
            "id": "bd80c133e7ffd43d",
            "type": "leaf",
            "state": {
              "type": "markdown",
              "state": {
                "file": "Comptia/A+/1.3 Mobile Device Network.md",
                "mode": "source",
                "source": false
              },
              "icon": "lucide-file",
              "title": "1.3 Mobile Device Network"
            }
          },
          {
            "id": "1a92f8b2aa8e1a93",
            "type": "leaf",
            "state": {
              "type": "markdown",
              "state": {
                "file": "Comptia/A+/AIO book/Electrostatic Discharge (ESD).md",
                "mode": "source",
                "source": false
              },
              "icon": "lucide-file",
              "title": "Electrostatic Discharge (ESD)"
            }
          }
        ],
        "currentTab": 2
      }
    ],
    "direction": "vertical"
  },
  "left": {
    "id": "6c04149b7b35df83",
    "type": "split",
    "children": [
      {
        "id": "a203df075d5d723a",
        "type": "tabs",
        "children": [
          {
            "id": "4e8286d7dfebfffe",
            "type": "leaf",
            "state": {
              "type": "file-explorer",
              "state": {
                "sortOrder": "alphabetical",
                "autoReveal": false
              },
              "icon": "lucide-folder-closed",
              "title": "Files"
            }
          },
          {
            "id": "93a90b9c2ab1d8a5",
            "type": "leaf",
            "state": {
              "type": "search",
              "state": {
                "query": "",
                "matchingCase": false,
                "explainSearch": false,
                "collapseAll": false,
                "extraContext": false,
                "sortOrder": "alphabetical"
              },
              "icon": "lucide-search",
              "title": "Search"
            }
          },
          {
            "id": "312b3f8229301532",
            "type": "leaf",
            "state": {
              "type": "bookmarks",
              "state": {},
              "icon": "lucide-bookmark",
              "title": "Bookmarks"
            }
          }
        ]
      }
    ],
    "direction": "horizontal",
    "width": 300
  },
  "right": {
    "id": "fe9e655de615d685",
    "type": "split",
    "children": [
      {
        "id": "910acc56e7f676da",
        "type": "tabs",
        "children": [
          {
            "id": "472f4a6927e911c3",
            "type": "leaf",
            "state": {
              "type": "backlink",
              "state": {
                "file": "Comptia/A+/1.1 Laptop Hardware.md",
                "collapseAll": false,
                "extraContext": false,
                "sortOrder": "alphabetical",
                "showSearch": false,
                "searchQuery": "",
                "backlinkCollapsed": false,
                "unlinkedCollapsed": true
              },
              "icon": "links-coming-in",
              "title": "Backlinks for 1.1 Laptop Hardware"
            }
          },
          {
            "id": "4764d65bf7eacdb6",
            "type": "leaf",
            "state": {
              "type": "outgoing-link",
              "state": {
                "file": "Comptia/A+/1.1 Laptop Hardware.md",
                "linksCollapsed": false,
                "unlinkedCollapsed": true
              },
              "icon": "links-going-out",
              "title": "Outgoing links from 1.1 Laptop Hardware"
            }
          },
          {
            "id": "910ef65292ded344",
            "type": "leaf",
            "state": {
              "type": "tag",
              "state": {
                "sortOrder": "frequency",
                "useHierarchy": true,
                "showSearch": false,
                "searchQuery": ""
              },
              "icon": "lucide-tags",
              "title": "Tags"
            }
          },
          {
            "id": "90d32245dd3e9486",
            "type": "leaf",
            "state": {
              "type": "outline",
              "state": {
                "file": "Comptia/A+/1.1 Laptop Hardware.md",
                "followCursor": false,
                "showSearch": false,
                "searchQuery": ""
              },
              "icon": "lucide-list",
              "title": "Outline of 1.1 Laptop Hardware"
            }
          }
        ]
      }
    ],
    "direction": "horizontal",
    "width": 300,
    "collapsed": true
  },
  "left-ribbon": {
    "hiddenItems": {
      "switcher:Open quick switcher": false,
      "graph:Open graph view": false,
      "canvas:Create new canvas": false,
      "daily-notes:Open today's daily note": false,
      "templates:Insert template": false,
      "command-palette:Open command palette": false
    }
  },
  "active": "4e8286d7dfebfffe",
  "lastOpenFiles": [
    "Comptia/A+/AIO book/Media",
    "Comptia/A+/AIO book/Media/Technical toolkit.png",
    "Comptia/A+/AIO book/Info.md",
    "Comptia/A+/AIO book/Electrostatic Discharge (ESD).md",
    "Comptia/A+/Professor Messer/1.1 Laptop Hardware.md",
    "Comptia/A+/AIO book",
    "Comptia/A+/Professor Messer/2.1 Introduction to IP.md",
    "Comptia/A+/Professor Messer",
    "Comptia/A+/Professor Messer/1.3 Mobile Device Network.md",
    "Comptia/A+/Professor Messer/1.2 connecting mobile devices.md",
    "Unrealistic Roadmap.md",
    "templates/Untitled.md",
    "templates",
    "Comptia/A+",
    "Comptia"
  ]
}